[ {
  "id" : 2,
  "email" : "rizki@gmail.com",
  "status" : "WAITING",
  "availability" : null
}, {
  "id" : 2,
  "email" : "novan@gmail.com",
  "status" : "WAITING",
  "availability" : null
}, {
  "id" : 2,
  "email" : "fernando@gmail.com",
  "status" : "WAITING",
  "availability" : null
}, {
  "id" : 2,
  "email" : "arif@gmail.com",
  "status" : "WAITING",
  "availability" : null
}, {
  "id" : 2,
  "email" : "jere@gmail.com",
  "status" : "WAITING",
  "availability" : null
}, {
  "id" : 3,
  "email" : "rizki@gmail.com",
  "status" : "WAITING",
  "availability" : null
}, {
  "id" : 3,
  "email" : "novan@gmail.com",
  "status" : "WAITING",
  "availability" : null
}, {
  "id" : 3,
  "email" : "ucong@gmail.com",
  "status" : "WAITING",
  "availability" : null
}, {
  "id" : 4,
  "email" : "novan@gmail.com",
  "status" : "CONFIRMED",
  "availability" : [ 1480417200000 ]
}, {
  "id" : 4,
  "email" : "rizki@gmail.com",
  "status" : "WAITING",
  "availability" : null
}, {
  "id" : 4,
  "email" : "fernando@gmail.com",
  "status" : "WAITING",
  "availability" : null
}, {
  "id" : 4,
  "email" : "arif@gmail.com",
  "status" : "WAITING",
  "availability" : null
}, {
  "id" : 4,
  "email" : "ucong@gmail.com",
  "status" : "WAITING",
  "availability" : null
} ]